{
  "script": "alfa",
  "batch": "alfaAllRest",
  "what": "alfa",
  "strict": true,
  "testDate": "2022-01-20",
  "timeStamp": "1d0or",
  "logCount": 8,
  "logSize": 599,
  "prohibitedCount": 0,
  "visitTimeoutCount": 0,
  "visitRejectionCount": 0,
  "presses": 0,
  "amountRead": 0,
  "acts": [
    {
      "type": "launch",
      "which": "chromium",
      "what": "used for most tests"
    },
    {
      "type": "url",
      "which": "https://www.scotiabank.com/ca/en/personal.html",
      "what": "Scotiabank (VEIGX)",
      "result": "https://www.scotiabank.com/ca/en/personal.html"
    },
    {
      "type": "test",
      "which": "alfa",
      "what": "alfa",
      "url": "https://www.scotiabank.com/ca/en/personal.html",
      "result": [
        {
          "index": 42,
          "verdict": "failed",
          "rule": {
            "ruleID": "r12",
            "ruleSummary": "Buttons have an accessible name",
            "scope": "component",
            "uri": "https://alfa.siteimprove.com/rules/sia-r12",
            "requirements": [
              {
                "uri": "https://www.w3.org/TR/WCAG/#name-role-value",
                "chapter": "4.1.2",
                "title": "Name, Role, Value"
              }
            ]
          },
          "target": {
            "type": "element",
            "tagName": "button",
            "path": "/html[1]/body[1]/div[1]/header[1]/div[1]/header[1]/div[1]/form[1]/button[1]",
            "codeLines": [
              "<button type=\"button\" class=\"s--submit\" data-submit=\"\">",
              "  <img class=\"s--submit--icon\" src=\"data:image/svg+xml;base64,PD94bWwgdmVyc2lvbj0iMS4wIiBlbmNvZGluZ...",
              "</button>"
            ]
          }
        },
        {
          "index": 719,
          "verdict": "failed",
          "rule": {
            "ruleID": "r3",
            "ruleSummary": "id attributes have a unique value",
            "scope": "component",
            "uri": "https://alfa.siteimprove.com/rules/sia-r3",
            "requirements": [
              {
                "uri": "https://www.w3.org/TR/WCAG/#parsing",
                "chapter": "4.1.1",
                "title": "Parsing"
              },
              {
                "uri": "https://www.w3.org/WAI/WCAG21/Techniques/html/H93",
                "name": "H93",
                "title": "Ensuring that id attributes are unique on a Web page"
              }
            ]
          },
          "target": {
            "type": "element",
            "tagName": "li",
            "path": "/html[1]/body[1]/div[1]/main[1]/div[3]/div[1]/div[1]/ul[1]/li[1]",
            "codeLines": [
              "<li class=\"rec--tab\" role=\"tab\" aria-selected=\"true\" aria-controls=\"featured-panel\" id=\"featured\">",
              "  <a href=\"javascript:void(0);\" class=\"tab-element\">",
              "    Featured",
              "  </a>",
              "</li>"
            ]
          }
        },
        {
          "index": 720,
          "verdict": "failed",
          "rule": {
            "ruleID": "r3",
            "ruleSummary": "id attributes have a unique value",
            "scope": "component",
            "uri": "https://alfa.siteimprove.com/rules/sia-r3",
            "requirements": [
              {
                "uri": "https://www.w3.org/TR/WCAG/#parsing",
                "chapter": "4.1.1",
                "title": "Parsing"
              },
              {
                "uri": "https://www.w3.org/WAI/WCAG21/Techniques/html/H93",
                "name": "H93",
                "title": "Ensuring that id attributes are unique on a Web page"
              }
            ]
          },
          "target": {
            "type": "element",
            "tagName": "li",
            "path": "/html[1]/body[1]/div[1]/main[1]/div[3]/div[1]/div[1]/ul[1]/li[2]",
            "codeLines": [
              "<li class=\"rec--tab\" role=\"tab\" aria-selected=\"false\" aria-controls=\"accounts-panel\" id=\"accounts\">",
              "  <a href=\"javascript:void(0);\" class=\"tab-element\">",
              "    Accounts",
              "  </a>",
              "</li>"
            ]
          }
        },
        {
          "index": 721,
          "verdict": "failed",
          "rule": {
            "ruleID": "r3",
            "ruleSummary": "id attributes have a unique value",
            "scope": "component",
            "uri": "https://alfa.siteimprove.com/rules/sia-r3",
            "requirements": [
              {
                "uri": "https://www.w3.org/TR/WCAG/#parsing",
                "chapter": "4.1.1",
                "title": "Parsing"
              },
              {
                "uri": "https://www.w3.org/WAI/WCAG21/Techniques/html/H93",
                "name": "H93",
                "title": "Ensuring that id attributes are unique on a Web page"
              }
            ]
          },
          "target": {
            "type": "element",
            "tagName": "li",
            "path": "/html[1]/body[1]/div[1]/main[1]/div[3]/div[1]/div[1]/ul[1]/li[3]",
            "codeLines": [
              "<li class=\"rec--tab\" role=\"tab\" aria-selected=\"false\" aria-controls=\"credit-cards-panel\" id=\"Credit...",
              "  <a href=\"javascript:void(0);\" class=\"tab-element\">",
              "    Credit cards",
              "  </a>",
              "</li>"
            ]
          }
        },
        {
          "index": 722,
          "verdict": "failed",
          "rule": {
            "ruleID": "r3",
            "ruleSummary": "id attributes have a unique value",
            "scope": "component",
            "uri": "https://alfa.siteimprove.com/rules/sia-r3",
            "requirements": [
              {
                "uri": "https://www.w3.org/TR/WCAG/#parsing",
                "chapter": "4.1.1",
                "title": "Parsing"
              },
              {
                "uri": "https://www.w3.org/WAI/WCAG21/Techniques/html/H93",
                "name": "H93",
                "title": "Ensuring that id attributes are unique on a Web page"
              }
            ]
          },
          "target": {
            "type": "element",
            "tagName": "li",
            "path": "/html[1]/body[1]/div[1]/main[1]/div[3]/div[1]/div[1]/ul[1]/li[4]",
            "codeLines": [
              "<li class=\"rec--tab\" role=\"tab\" aria-selected=\"false\" aria-controls=\"borrowing-panel\" id=\"borrowing...",
              "  <a href=\"javascript:void(0);\" class=\"tab-element\">",
              "    Borrowing",
              "  </a>",
              "</li>"
            ]
          }
        },
        {
          "index": 723,
          "verdict": "failed",
          "rule": {
            "ruleID": "r3",
            "ruleSummary": "id attributes have a unique value",
            "scope": "component",
            "uri": "https://alfa.siteimprove.com/rules/sia-r3",
            "requirements": [
              {
                "uri": "https://www.w3.org/TR/WCAG/#parsing",
                "chapter": "4.1.1",
                "title": "Parsing"
              },
              {
                "uri": "https://www.w3.org/WAI/WCAG21/Techniques/html/H93",
                "name": "H93",
                "title": "Ensuring that id attributes are unique on a Web page"
              }
            ]
          },
          "target": {
            "type": "element",
            "tagName": "li",
            "path": "/html[1]/body[1]/div[1]/main[1]/div[3]/div[1]/div[1]/ul[1]/li[5]",
            "codeLines": [
              "<li class=\"rec--tab\" role=\"tab\" aria-selected=\"false\" aria-controls=\"investments-panel\" id=\"investm...",
              "  <a href=\"javascript:void(0);\" class=\"tab-element\">",
              "    Investments",
              "  </a>",
              "</li>"
            ]
          }
        },
        {
          "index": 724,
          "verdict": "failed",
          "rule": {
            "ruleID": "r3",
            "ruleSummary": "id attributes have a unique value",
            "scope": "component",
            "uri": "https://alfa.siteimprove.com/rules/sia-r3",
            "requirements": [
              {
                "uri": "https://www.w3.org/TR/WCAG/#parsing",
                "chapter": "4.1.1",
                "title": "Parsing"
              },
              {
                "uri": "https://www.w3.org/WAI/WCAG21/Techniques/html/H93",
                "name": "H93",
                "title": "Ensuring that id attributes are unique on a Web page"
              }
            ]
          },
          "target": {
            "type": "element",
            "tagName": "li",
            "path": "/html[1]/body[1]/div[1]/main[1]/div[3]/div[1]/div[1]/ul[1]/li[6]",
            "codeLines": [
              "<li class=\"rec--tab\" role=\"tab\" aria-selected=\"false\" aria-controls=\"learning-panel\" id=\"learning\">",
              "  <a href=\"javascript:void(0);\" class=\"tab-element\">",
              "    Learning",
              "  </a>",
              "</li>"
            ]
          }
        },
        {
          "index": 725,
          "verdict": "failed",
          "rule": {
            "ruleID": "r3",
            "ruleSummary": "id attributes have a unique value",
            "scope": "component",
            "uri": "https://alfa.siteimprove.com/rules/sia-r3",
            "requirements": [
              {
                "uri": "https://www.w3.org/TR/WCAG/#parsing",
                "chapter": "4.1.1",
                "title": "Parsing"
              },
              {
                "uri": "https://www.w3.org/WAI/WCAG21/Techniques/html/H93",
                "name": "H93",
                "title": "Ensuring that id attributes are unique on a Web page"
              }
            ]
          },
          "target": {
            "type": "element",
            "tagName": "option",
            "path": "/html[1]/body[1]/div[1]/main[1]/div[3]/div[1]/div[1]/div[1]/select[1]/option[1]",
            "codeLines": [
              "<option role=\"tab\" aria-controls=\"featured-panel\" aria-selected=\"true\" id=\"featured\" class=\"option-...",
              "  Featured",
              "</option>"
            ]
          }
        },
        {
          "index": 726,
          "verdict": "failed",
          "rule": {
            "ruleID": "r3",
            "ruleSummary": "id attributes have a unique value",
            "scope": "component",
            "uri": "https://alfa.siteimprove.com/rules/sia-r3",
            "requirements": [
              {
                "uri": "https://www.w3.org/TR/WCAG/#parsing",
                "chapter": "4.1.1",
                "title": "Parsing"
              },
              {
                "uri": "https://www.w3.org/WAI/WCAG21/Techniques/html/H93",
                "name": "H93",
                "title": "Ensuring that id attributes are unique on a Web page"
              }
            ]
          },
          "target": {
            "type": "element",
            "tagName": "option",
            "path": "/html[1]/body[1]/div[1]/main[1]/div[3]/div[1]/div[1]/div[1]/select[1]/option[2]",
            "codeLines": [
              "<option aria-controls=\"accounts-panel\" id=\"accounts\" class=\"option-element\" aria-selected=\"false\" v...",
              "  Accounts",
              "</option>"
            ]
          }
        },
        {
          "index": 727,
          "verdict": "failed",
          "rule": {
            "ruleID": "r3",
            "ruleSummary": "id attributes have a unique value",
            "scope": "component",
            "uri": "https://alfa.siteimprove.com/rules/sia-r3",
            "requirements": [
              {
                "uri": "https://www.w3.org/TR/WCAG/#parsing",
                "chapter": "4.1.1",
                "title": "Parsing"
              },
              {
                "uri": "https://www.w3.org/WAI/WCAG21/Techniques/html/H93",
                "name": "H93",
                "title": "Ensuring that id attributes are unique on a Web page"
              }
            ]
          },
          "target": {
            "type": "element",
            "tagName": "option",
            "path": "/html[1]/body[1]/div[1]/main[1]/div[3]/div[1]/div[1]/div[1]/select[1]/option[3]",
            "codeLines": [
              "<option aria-controls=\"credit-cards-panel\" id=\"CreditCards-eng\" class=\"option-element\" aria-selecte...",
              "  Credit cards",
              "</option>"
            ]
          }
        },
        {
          "index": 728,
          "verdict": "failed",
          "rule": {
            "ruleID": "r3",
            "ruleSummary": "id attributes have a unique value",
            "scope": "component",
            "uri": "https://alfa.siteimprove.com/rules/sia-r3",
            "requirements": [
              {
                "uri": "https://www.w3.org/TR/WCAG/#parsing",
                "chapter": "4.1.1",
                "title": "Parsing"
              },
              {
                "uri": "https://www.w3.org/WAI/WCAG21/Techniques/html/H93",
                "name": "H93",
                "title": "Ensuring that id attributes are unique on a Web page"
              }
            ]
          },
          "target": {
            "type": "element",
            "tagName": "option",
            "path": "/html[1]/body[1]/div[1]/main[1]/div[3]/div[1]/div[1]/div[1]/select[1]/option[4]",
            "codeLines": [
              "<option aria-controls=\"borrowing-panel\" id=\"borrowing\" class=\"option-element\" aria-selected=\"false\"...",
              "  Borrowing",
              "</option>"
            ]
          }
        },
        {
          "index": 729,
          "verdict": "failed",
          "rule": {
            "ruleID": "r3",
            "ruleSummary": "id attributes have a unique value",
            "scope": "component",
            "uri": "https://alfa.siteimprove.com/rules/sia-r3",
            "requirements": [
              {
                "uri": "https://www.w3.org/TR/WCAG/#parsing",
                "chapter": "4.1.1",
                "title": "Parsing"
              },
              {
                "uri": "https://www.w3.org/WAI/WCAG21/Techniques/html/H93",
                "name": "H93",
                "title": "Ensuring that id attributes are unique on a Web page"
              }
            ]
          },
          "target": {
            "type": "element",
            "tagName": "option",
            "path": "/html[1]/body[1]/div[1]/main[1]/div[3]/div[1]/div[1]/div[1]/select[1]/option[5]",
            "codeLines": [
              "<option aria-controls=\"investments-panel\" id=\"investments\" class=\"option-element\" aria-selected=\"fa...",
              "  Investments",
              "</option>"
            ]
          }
        },
        {
          "index": 730,
          "verdict": "failed",
          "rule": {
            "ruleID": "r3",
            "ruleSummary": "id attributes have a unique value",
            "scope": "component",
            "uri": "https://alfa.siteimprove.com/rules/sia-r3",
            "requirements": [
              {
                "uri": "https://www.w3.org/TR/WCAG/#parsing",
                "chapter": "4.1.1",
                "title": "Parsing"
              },
              {
                "uri": "https://www.w3.org/WAI/WCAG21/Techniques/html/H93",
                "name": "H93",
                "title": "Ensuring that id attributes are unique on a Web page"
              }
            ]
          },
          "target": {
            "type": "element",
            "tagName": "option",
            "path": "/html[1]/body[1]/div[1]/main[1]/div[3]/div[1]/div[1]/div[1]/select[1]/option[6]",
            "codeLines": [
              "<option aria-controls=\"learning-panel\" id=\"learning\" class=\"option-element\" aria-selected=\"false\" v...",
              "  Learning",
              "</option>"
            ]
          }
        },
        {
          "index": 749,
          "verdict": "failed",
          "rule": {
            "ruleID": "r3",
            "ruleSummary": "id attributes have a unique value",
            "scope": "component",
            "uri": "https://alfa.siteimprove.com/rules/sia-r3",
            "requirements": [
              {
                "uri": "https://www.w3.org/TR/WCAG/#parsing",
                "chapter": "4.1.1",
                "title": "Parsing"
              },
              {
                "uri": "https://www.w3.org/WAI/WCAG21/Techniques/html/H93",
                "name": "H93",
                "title": "Ensuring that id attributes are unique on a Web page"
              }
            ]
          },
          "target": {
            "type": "element",
            "tagName": "a",
            "path": "/html[1]/body[1]/div[1]/main[1]/div[3]/div[1]/div[1]/div[4]/div[1]/div[1]/div[5]/div[1]/div[1]/div[1]/div[1]/div[1]/div[1]/div[2]/div[2]/a[1]",
            "codeLines": [
              "<a target=\"_self\" id=\"HP-borrowing-SelectPay\" class=\"standalone-link\" href=\"/ca/en/personal/credit-...",
              "  Learn more about SelectPay",
              "  <span class=\"fas fa-chevron-right\"></span>",
              "  <span class=\"sr-only\"></span>",
              "</a>"
            ]
          }
        },
        {
          "index": 755,
          "verdict": "failed",
          "rule": {
            "ruleID": "r3",
            "ruleSummary": "id attributes have a unique value",
            "scope": "component",
            "uri": "https://alfa.siteimprove.com/rules/sia-r3",
            "requirements": [
              {
                "uri": "https://www.w3.org/TR/WCAG/#parsing",
                "chapter": "4.1.1",
                "title": "Parsing"
              },
              {
                "uri": "https://www.w3.org/WAI/WCAG21/Techniques/html/H93",
                "name": "H93",
                "title": "Ensuring that id attributes are unique on a Web page"
              }
            ]
          },
          "target": {
            "type": "element",
            "tagName": "a",
            "path": "/html[1]/body[1]/div[1]/main[1]/div[3]/div[1]/div[1]/div[5]/div[1]/div[1]/div[3]/div[1]/div[1]/div[5]/div[1]/div[1]/div[1]/div[2]/div[2]/a[1]",
            "codeLines": [
              "<a target=\"_self\" id=\"HP-borrowing-SelectPay\" class=\"standalone-link\" href=\"/ca/en/personal/loans-l...",
              "  Launch auto loan calculator",
              "  <span class=\"fas fa-chevron-right\"></span>",
              "  <span class=\"sr-only\"></span>",
              "</a>"
            ]
          }
        },
        {
          "index": 807,
          "verdict": "failed",
          "rule": {
            "ruleID": "r42",
            "ruleSummary": "Elements with a role have required parent",
            "scope": "component",
            "uri": "https://alfa.siteimprove.com/rules/sia-r42",
            "requirements": [
              {
                "uri": "https://www.w3.org/TR/WCAG/#info-and-relationships",
                "chapter": "1.3.1",
                "title": "Info and Relationships"
              }
            ]
          },
          "target": {
            "type": "element",
            "tagName": "a",
            "path": "/html[1]/body[1]/div[1]/nav[1]/div[1]/ul[1]/li[1]/a[1]",
            "codeLines": [
              "<a id=\"nav-item-1\" href=\"/ca/en/personal/advice-plus.html\" class=\"mm--nav-link\" data-toggle=\"mm--dr...",
              "  <span>",
              "    Advice+",
              "  </span>",
              "</a>"
            ]
          }
        },
        {
          "index": 809,
          "verdict": "failed",
          "rule": {
            "ruleID": "r42",
            "ruleSummary": "Elements with a role have required parent",
            "scope": "component",
            "uri": "https://alfa.siteimprove.com/rules/sia-r42",
            "requirements": [
              {
                "uri": "https://www.w3.org/TR/WCAG/#info-and-relationships",
                "chapter": "1.3.1",
                "title": "Info and Relationships"
              }
            ]
          },
          "target": {
            "type": "element",
            "tagName": "a",
            "path": "/html[1]/body[1]/div[1]/nav[1]/div[1]/ul[1]/li[2]/a[1]",
            "codeLines": [
              "<a id=\"nav-item-2\" href=\"/ca/en/personal/bank-accounts.html\" class=\"mm--nav-link\" data-toggle=\"mm--...",
              "  <span>",
              "    Bank Accounts",
              "  </span>",
              "</a>"
            ]
          }
        },
        {
          "index": 811,
          "verdict": "failed",
          "rule": {
            "ruleID": "r42",
            "ruleSummary": "Elements with a role have required parent",
            "scope": "component",
            "uri": "https://alfa.siteimprove.com/rules/sia-r42",
            "requirements": [
              {
                "uri": "https://www.w3.org/TR/WCAG/#info-and-relationships",
                "chapter": "1.3.1",
                "title": "Info and Relationships"
              }
            ]
          },
          "target": {
            "type": "element",
            "tagName": "a",
            "path": "/html[1]/body[1]/div[1]/nav[1]/div[1]/ul[1]/li[3]/a[1]",
            "codeLines": [
              "<a id=\"nav-item-3\" href=\"/ca/en/personal/credit-cards.html\" class=\"mm--nav-link\" data-toggle=\"mm--d...",
              "  <span>",
              "    Credit Cards",
              "  </span>",
              "</a>"
            ]
          }
        },
        {
          "index": 813,
          "verdict": "failed",
          "rule": {
            "ruleID": "r42",
            "ruleSummary": "Elements with a role have required parent",
            "scope": "component",
            "uri": "https://alfa.siteimprove.com/rules/sia-r42",
            "requirements": [
              {
                "uri": "https://www.w3.org/TR/WCAG/#info-and-relationships",
                "chapter": "1.3.1",
                "title": "Info and Relationships"
              }
            ]
          },
          "target": {
            "type": "element",
            "tagName": "a",
            "path": "/html[1]/body[1]/div[1]/nav[1]/div[1]/ul[1]/li[4]/a[1]",
            "codeLines": [
              "<a id=\"nav-item-4\" href=\"/ca/en/personal/mortgages.html\" class=\"mm--nav-link\" data-toggle=\"mm--drop...",
              "  <span>",
              "    Mortgages",
              "  </span>",
              "</a>"
            ]
          }
        },
        {
          "index": 815,
          "verdict": "failed",
          "rule": {
            "ruleID": "r42",
            "ruleSummary": "Elements with a role have required parent",
            "scope": "component",
            "uri": "https://alfa.siteimprove.com/rules/sia-r42",
            "requirements": [
              {
                "uri": "https://www.w3.org/TR/WCAG/#info-and-relationships",
                "chapter": "1.3.1",
                "title": "Info and Relationships"
              }
            ]
          },
          "target": {
            "type": "element",
            "tagName": "a",
            "path": "/html[1]/body[1]/div[1]/nav[1]/div[1]/ul[1]/li[5]/a[1]",
            "codeLines": [
              "<a id=\"nav-item-5\" href=\"/ca/en/personal/loans-lines.html\" class=\"mm--nav-link\" data-toggle=\"mm--dr...",
              "  <span>",
              "    Loans & Lines of Credit",
              "  </span>",
              "</a>"
            ]
          }
        },
        {
          "index": 817,
          "verdict": "failed",
          "rule": {
            "ruleID": "r42",
            "ruleSummary": "Elements with a role have required parent",
            "scope": "component",
            "uri": "https://alfa.siteimprove.com/rules/sia-r42",
            "requirements": [
              {
                "uri": "https://www.w3.org/TR/WCAG/#info-and-relationships",
                "chapter": "1.3.1",
                "title": "Info and Relationships"
              }
            ]
          },
          "target": {
            "type": "element",
            "tagName": "a",
            "path": "/html[1]/body[1]/div[1]/nav[1]/div[1]/ul[1]/li[6]/a[1]",
            "codeLines": [
              "<a id=\"nav-item-6\" href=\"/ca/en/personal/investing.html\" class=\"mm--nav-link\" data-toggle=\"mm--drop...",
              "  <span>",
              "    Investments",
              "  </span>",
              "</a>"
            ]
          }
        },
        {
          "index": 819,
          "verdict": "failed",
          "rule": {
            "ruleID": "r42",
            "ruleSummary": "Elements with a role have required parent",
            "scope": "component",
            "uri": "https://alfa.siteimprove.com/rules/sia-r42",
            "requirements": [
              {
                "uri": "https://www.w3.org/TR/WCAG/#info-and-relationships",
                "chapter": "1.3.1",
                "title": "Info and Relationships"
              }
            ]
          },
          "target": {
            "type": "element",
            "tagName": "a",
            "path": "/html[1]/body[1]/div[1]/nav[1]/div[1]/ul[1]/li[7]/a[1]",
            "codeLines": [
              "<a id=\"nav-item-7\" href=\"/ca/en/personal/creditor-insurance/creditor-insurance.html\" class=\"mm--nav...",
              "  <span>",
              "    Insurance",
              "  </span>",
              "</a>"
            ]
          }
        },
        {
          "index": 821,
          "verdict": "failed",
          "rule": {
            "ruleID": "r42",
            "ruleSummary": "Elements with a role have required parent",
            "scope": "component",
            "uri": "https://alfa.siteimprove.com/rules/sia-r42",
            "requirements": [
              {
                "uri": "https://www.w3.org/TR/WCAG/#info-and-relationships",
                "chapter": "1.3.1",
                "title": "Info and Relationships"
              }
            ]
          },
          "target": {
            "type": "element",
            "tagName": "a",
            "path": "/html[1]/body[1]/div[1]/nav[1]/div[1]/ul[1]/li[8]/a[1]",
            "codeLines": [
              "<a id=\"nav-item-8\" href=\"/ca/en/personal/programs-services.html\" class=\"mm--nav-link\" data-toggle=\"...",
              "  <span>",
              "    Programs",
              "  </span>",
              "</a>"
            ]
          }
        },
        {
          "index": 823,
          "verdict": "failed",
          "rule": {
            "ruleID": "r42",
            "ruleSummary": "Elements with a role have required parent",
            "scope": "component",
            "uri": "https://alfa.siteimprove.com/rules/sia-r42",
            "requirements": [
              {
                "uri": "https://www.w3.org/TR/WCAG/#info-and-relationships",
                "chapter": "1.3.1",
                "title": "Info and Relationships"
              }
            ]
          },
          "target": {
            "type": "element",
            "tagName": "a",
            "path": "/html[1]/body[1]/div[1]/nav[1]/div[1]/ul[1]/li[9]/a[1]",
            "codeLines": [
              "<a id=\"nav-item-9\" href=\"/ca/en/personal/rates-prices.html\" class=\"mm--nav-link\" data-toggle=\"mm--d...",
              "  <span>",
              "    Rates & Fees",
              "  </span>",
              "</a>"
            ]
          }
        },
        {
          "index": 967,
          "verdict": "failed",
          "rule": {
            "ruleID": "r61",
            "ruleSummary": "Documents start with a level 1 heading",
            "scope": "page",
            "uri": "https://alfa.siteimprove.com/rules/sia-r61",
            "requirements": []
          },
          "target": {
            "type": "document",
            "tagName": "",
            "path": "/",
            "codeLines": [
              "#document",
              "  <!doctype html>",
              "...",
              "  </html>"
            ]
          }
        },
        {
          "index": 1045,
          "verdict": "failed",
          "rule": {
            "ruleID": "r68",
            "ruleSummary": "Elements with a role have required children",
            "scope": "component",
            "uri": "https://alfa.siteimprove.com/rules/sia-r68",
            "requirements": [
              {
                "uri": "https://www.w3.org/TR/WCAG/#info-and-relationships",
                "chapter": "1.3.1",
                "title": "Info and Relationships"
              }
            ]
          },
          "target": {
            "type": "element",
            "tagName": "ul",
            "path": "/html[1]/body[1]/div[1]/header[1]/div[1]/div[1]/div[1]/div[1]/ul[1]",
            "codeLines": [
              "<ul>",
              "  <nav>",
              "    <li>",
              "      <a href=\"/ca/en/personal.html\" class=\"nav-link active\" aria-label=\"Personal\">",
              "        Personal",
              "      </a>",
              "    </li>",
              "  </nav>",
              "  <nav>",
              "    <li>",
              "      <a href=\"/ca/en/small-business.html\" class=\"nav-link\" aria-label=\"Small Business\">",
              "        Small Business",
              "      </a>",
              "    </li>",
              "  </nav>",
              "  <nav>",
              "    <li>",
              "      <a href=\"/ca/en/commercial-banking.html\" class=\"nav-link\" aria-label=\"Commercial\">",
              "        Commercial",
              "      </a>",
              "    </li>",
              "  </nav>",
              "  <nav>",
              "    <li>",
              "      <a href=\"https://www.gbm.scotiabank.com/en.html\" class=\"nav-link\" aria-label=\"Global Markets\"...",
              "        Global Markets",
              "      </a>",
              "    </li>",
              "  </nav>",
              "  <nav>",
              "    <li>",
              "      <a href=\"https://globalwealth.scotiabank.com/en/home.html\" class=\"nav-link\" aria-label=\"Globa...",
              "        Global Wealth",
              "      </a>",
              "    </li>",
              "  </nav>",
              "  <nav>",
              "    <li>",
              "      <a href=\"/ca/en/about.html\" class=\"nav-link\" aria-label=\"About Us\">",
              "        About Us",
              "      </a>",
              "    </li>",
              "  </nav>",
              "  <nav>",
              "    <li>",
              "      <a href=\"/ca/en/about/investors-shareholders.html\" class=\"nav-link\" aria-label=\"Investors\">",
              "        Investors",
              "      </a>",
              "    </li>",
              "  </nav>",
              "</ul>"
            ]
          }
        },
        {
          "index": 1061,
          "verdict": "failed",
          "rule": {
            "ruleID": "r78",
            "ruleSummary": "Headings of same level have text content between them",
            "scope": "component",
            "uri": "https://alfa.siteimprove.com/rules/sia-r78",
            "requirements": []
          },
          "target": {
            "type": "element",
            "tagName": "h2",
            "path": "/html[1]/body[1]/div[1]/main[1]/div[3]/div[1]/div[1]/div[2]/div[1]/div[1]/div[1]/div[1]/h2[1]",
            "codeLines": [
              "<h2 class=\"text-none text-black\">",
              "  Featured",
              "  <br>",
              "</h2>"
            ]
          }
        },
        {
          "index": 1062,
          "verdict": "failed",
          "rule": {
            "ruleID": "r78",
            "ruleSummary": "Headings of same level have text content between them",
            "scope": "component",
            "uri": "https://alfa.siteimprove.com/rules/sia-r78",
            "requirements": []
          },
          "target": {
            "type": "element",
            "tagName": "h3",
            "path": "/html[1]/body[1]/div[1]/main[1]/div[3]/div[1]/div[1]/div[2]/div[1]/div[1]/div[3]/div[1]/div[1]/div[1]/div[1]/div[1]/div[1]/div[2]/div[1]/h3[1]",
            "codeLines": [
              "<h3>",
              "  <span class=\"subtitle-1\">",
              "    Count your savings while you count sheep",
              "  </span>",
              "</h3>"
            ]
          }
        },
        {
          "index": 1063,
          "verdict": "failed",
          "rule": {
            "ruleID": "r78",
            "ruleSummary": "Headings of same level have text content between them",
            "scope": "component",
            "uri": "https://alfa.siteimprove.com/rules/sia-r78",
            "requirements": []
          },
          "target": {
            "type": "element",
            "tagName": "h3",
            "path": "/html[1]/body[1]/div[1]/main[1]/div[3]/div[1]/div[1]/div[2]/div[1]/div[1]/div[3]/div[1]/div[1]/div[3]/div[1]/div[1]/div[1]/div[3]/div[1]/h3[1]",
            "codeLines": [
              "<h3>",
              "  <span class=\"subtitle-1\">",
              "    Welcome to a fresh start where it’s all possible",
              "  </span>",
              "</h3>"
            ]
          }
        },
        {
          "index": 1064,
          "verdict": "failed",
          "rule": {
            "ruleID": "r78",
            "ruleSummary": "Headings of same level have text content between them",
            "scope": "component",
            "uri": "https://alfa.siteimprove.com/rules/sia-r78",
            "requirements": []
          },
          "target": {
            "type": "element",
            "tagName": "h3",
            "path": "/html[1]/body[1]/div[1]/main[1]/div[3]/div[1]/div[1]/div[2]/div[1]/div[1]/div[3]/div[1]/div[1]/div[5]/div[1]/div[1]/div[1]/div[2]/div[1]/h3[1]",
            "codeLines": [
              "<h3>",
              "  <span class=\"subtitle-1\">",
              "    Put your financial worries to bed",
              "  </span>",
              "</h3>"
            ]
          }
        },
        {
          "index": 1065,
          "verdict": "failed",
          "rule": {
            "ruleID": "r78",
            "ruleSummary": "Headings of same level have text content between them",
            "scope": "component",
            "uri": "https://alfa.siteimprove.com/rules/sia-r78",
            "requirements": []
          },
          "target": {
            "type": "element",
            "tagName": "h3",
            "path": "/html[1]/body[1]/div[1]/main[1]/div[3]/div[1]/div[1]/div[2]/div[1]/div[1]/div[5]/div[1]/div[1]/div[1]/div[1]/div[1]/div[1]/div[2]/div[1]/h3[1]",
            "codeLines": [
              "<h3>",
              "  <span class=\"subtitle-1\">",
              "    Success for all women",
              "  </span>",
              "</h3>"
            ]
          }
        },
        {
          "index": 1066,
          "verdict": "failed",
          "rule": {
            "ruleID": "r78",
            "ruleSummary": "Headings of same level have text content between them",
            "scope": "component",
            "uri": "https://alfa.siteimprove.com/rules/sia-r78",
            "requirements": []
          },
          "target": {
            "type": "element",
            "tagName": "h3",
            "path": "/html[1]/body[1]/div[1]/main[1]/div[3]/div[1]/div[1]/div[2]/div[1]/div[1]/div[5]/div[1]/div[1]/div[3]/div[1]/div[1]/div[1]/div[3]/div[1]/h3[1]",
            "codeLines": [
              "<h3>",
              "  <span class=\"subtitle-1\">",
              "    <b>",
              "      Updated your home? You’re already an investor.",
              "    </b>",
              "  </span>",
              "</h3>"
            ]
          }
        },
        {
          "index": 1067,
          "verdict": "failed",
          "rule": {
            "ruleID": "r78",
            "ruleSummary": "Headings of same level have text content between them",
            "scope": "component",
            "uri": "https://alfa.siteimprove.com/rules/sia-r78",
            "requirements": []
          },
          "target": {
            "type": "element",
            "tagName": "h3",
            "path": "/html[1]/body[1]/div[1]/main[1]/div[3]/div[1]/div[1]/div[2]/div[1]/div[1]/div[5]/div[1]/div[1]/div[5]/div[1]/div[1]/div[1]/div[2]/div[1]/h3[1]",
            "codeLines": [
              "<h3>",
              "  <span class=\"subtitle-1\">",
              "    Check tuition off your worry list with $30,000",
              "    <sup>",
              "      ‡",
              "    </sup>",
              "  </span>",
              "</h3>"
            ]
          }
        },
        {
          "index": 1068,
          "verdict": "failed",
          "rule": {
            "ruleID": "r78",
            "ruleSummary": "Headings of same level have text content between them",
            "scope": "component",
            "uri": "https://alfa.siteimprove.com/rules/sia-r78",
            "requirements": []
          },
          "target": {
            "type": "element",
            "tagName": "h2",
            "path": "/html[1]/body[1]/div[1]/main[1]/div[4]/div[1]/div[1]/div[1]/div[2]/div[1]/div[2]/div[1]/div[1]/h2[1]",
            "codeLines": [
              "<h2 class=\"map--card-title\">",
              "  Locate branches, advisors, and ABMs",
              "</h2>"
            ]
          }
        },
        {
          "index": 1069,
          "verdict": "failed",
          "rule": {
            "ruleID": "r78",
            "ruleSummary": "Headings of same level have text content between them",
            "scope": "component",
            "uri": "https://alfa.siteimprove.com/rules/sia-r78",
            "requirements": []
          },
          "target": {
            "type": "element",
            "tagName": "h2",
            "path": "/html[1]/body[1]/div[1]/div[3]/div[1]/footer[1]/div[1]/div[1]/div[1]/div[1]/h2[1]",
            "codeLines": [
              "<h2 class=\"c--title\">",
              "  Have a question?",
              "</h2>"
            ]
          }
        },
        {
          "index": 1070,
          "verdict": "failed",
          "rule": {
            "ruleID": "r78",
            "ruleSummary": "Headings of same level have text content between them",
            "scope": "component",
            "uri": "https://alfa.siteimprove.com/rules/sia-r78",
            "requirements": []
          },
          "target": {
            "type": "element",
            "tagName": "h2",
            "path": "/html[1]/body[1]/div[1]/div[3]/div[1]/footer[1]/div[1]/div[1]/div[2]/div[1]/h2[1]",
            "codeLines": [
              "<h2 class=\"c--title\">",
              "  Call Scotiabank",
              "</h2>"
            ]
          }
        },
        {
          "index": 1071,
          "verdict": "failed",
          "rule": {
            "ruleID": "r78",
            "ruleSummary": "Headings of same level have text content between them",
            "scope": "component",
            "uri": "https://alfa.siteimprove.com/rules/sia-r78",
            "requirements": []
          },
          "target": {
            "type": "element",
            "tagName": "h2",
            "path": "/html[1]/body[1]/div[1]/div[3]/div[1]/footer[1]/div[1]/div[1]/div[3]/div[1]/h2[1]",
            "codeLines": [
              "<h2 class=\"c--title\">",
              "  Get advice",
              "</h2>"
            ]
          }
        },
        {
          "index": 1076,
          "verdict": "cantTell",
          "rule": {
            "ruleID": "r82",
            "ruleSummary": "Error message describes invalid form field value",
            "scope": "component",
            "uri": "https://alfa.siteimprove.com/rules/sia-r82",
            "requirements": [
              {
                "uri": "https://www.w3.org/TR/WCAG/#error-identification",
                "chapter": "3.3.1",
                "title": "Error Identification"
              }
            ]
          },
          "target": {
            "type": "element",
            "tagName": "input",
            "path": "/html[1]/body[1]/div[1]/header[1]/div[1]/header[1]/div[1]/form[1]/input[3]",
            "codeLines": [
              "<input type=\"text\" id=\"header__search\" class=\"s--input\" placeholder=\"Begin Your Search\">"
            ]
          }
        },
        {
          "index": 1088,
          "verdict": "cantTell",
          "rule": {
            "ruleID": "r87",
            "ruleSummary": "First focusable element is link to main content",
            "scope": "page",
            "uri": "https://alfa.siteimprove.com/rules/sia-r87",
            "requirements": [
              {
                "uri": "https://www.w3.org/WAI/WCAG21/Techniques/general/G1",
                "name": "G1",
                "title": "Adding a link at the top of each page that goes directly to the main content area"
              }
            ]
          },
          "target": {
            "type": "document",
            "tagName": "",
            "path": "/",
            "codeLines": [
              "#document",
              "  <!doctype html>",
              "...",
              "  </html>"
            ]
          }
        },
        {
          "index": 1094,
          "verdict": "failed",
          "rule": {
            "ruleID": "r90",
            "ruleSummary": "Element with presentational children has no focusable content",
            "scope": "component",
            "uri": "https://alfa.siteimprove.com/rules/sia-r90",
            "requirements": [
              {
                "uri": "https://www.w3.org/TR/WCAG/#info-and-relationships",
                "chapter": "1.3.1",
                "title": "Info and Relationships"
              },
              {
                "uri": "https://www.w3.org/TR/WCAG/#name-role-value",
                "chapter": "4.1.2",
                "title": "Name, Role, Value"
              }
            ]
          },
          "target": {
            "type": "element",
            "tagName": "li",
            "path": "/html[1]/body[1]/div[1]/main[1]/div[3]/div[1]/div[1]/ul[1]/li[1]",
            "codeLines": [
              "<li class=\"rec--tab\" role=\"tab\" aria-selected=\"true\" aria-controls=\"featured-panel\" id=\"featured\">",
              "  <a href=\"javascript:void(0);\" class=\"tab-element\">",
              "    Featured",
              "  </a>",
              "</li>"
            ]
          }
        },
        {
          "index": 1095,
          "verdict": "failed",
          "rule": {
            "ruleID": "r90",
            "ruleSummary": "Element with presentational children has no focusable content",
            "scope": "component",
            "uri": "https://alfa.siteimprove.com/rules/sia-r90",
            "requirements": [
              {
                "uri": "https://www.w3.org/TR/WCAG/#info-and-relationships",
                "chapter": "1.3.1",
                "title": "Info and Relationships"
              },
              {
                "uri": "https://www.w3.org/TR/WCAG/#name-role-value",
                "chapter": "4.1.2",
                "title": "Name, Role, Value"
              }
            ]
          },
          "target": {
            "type": "element",
            "tagName": "li",
            "path": "/html[1]/body[1]/div[1]/main[1]/div[3]/div[1]/div[1]/ul[1]/li[2]",
            "codeLines": [
              "<li class=\"rec--tab\" role=\"tab\" aria-selected=\"false\" aria-controls=\"accounts-panel\" id=\"accounts\">",
              "  <a href=\"javascript:void(0);\" class=\"tab-element\">",
              "    Accounts",
              "  </a>",
              "</li>"
            ]
          }
        },
        {
          "index": 1096,
          "verdict": "failed",
          "rule": {
            "ruleID": "r90",
            "ruleSummary": "Element with presentational children has no focusable content",
            "scope": "component",
            "uri": "https://alfa.siteimprove.com/rules/sia-r90",
            "requirements": [
              {
                "uri": "https://www.w3.org/TR/WCAG/#info-and-relationships",
                "chapter": "1.3.1",
                "title": "Info and Relationships"
              },
              {
                "uri": "https://www.w3.org/TR/WCAG/#name-role-value",
                "chapter": "4.1.2",
                "title": "Name, Role, Value"
              }
            ]
          },
          "target": {
            "type": "element",
            "tagName": "li",
            "path": "/html[1]/body[1]/div[1]/main[1]/div[3]/div[1]/div[1]/ul[1]/li[3]",
            "codeLines": [
              "<li class=\"rec--tab\" role=\"tab\" aria-selected=\"false\" aria-controls=\"credit-cards-panel\" id=\"Credit...",
              "  <a href=\"javascript:void(0);\" class=\"tab-element\">",
              "    Credit cards",
              "  </a>",
              "</li>"
            ]
          }
        },
        {
          "index": 1097,
          "verdict": "failed",
          "rule": {
            "ruleID": "r90",
            "ruleSummary": "Element with presentational children has no focusable content",
            "scope": "component",
            "uri": "https://alfa.siteimprove.com/rules/sia-r90",
            "requirements": [
              {
                "uri": "https://www.w3.org/TR/WCAG/#info-and-relationships",
                "chapter": "1.3.1",
                "title": "Info and Relationships"
              },
              {
                "uri": "https://www.w3.org/TR/WCAG/#name-role-value",
                "chapter": "4.1.2",
                "title": "Name, Role, Value"
              }
            ]
          },
          "target": {
            "type": "element",
            "tagName": "li",
            "path": "/html[1]/body[1]/div[1]/main[1]/div[3]/div[1]/div[1]/ul[1]/li[4]",
            "codeLines": [
              "<li class=\"rec--tab\" role=\"tab\" aria-selected=\"false\" aria-controls=\"borrowing-panel\" id=\"borrowing...",
              "  <a href=\"javascript:void(0);\" class=\"tab-element\">",
              "    Borrowing",
              "  </a>",
              "</li>"
            ]
          }
        },
        {
          "index": 1098,
          "verdict": "failed",
          "rule": {
            "ruleID": "r90",
            "ruleSummary": "Element with presentational children has no focusable content",
            "scope": "component",
            "uri": "https://alfa.siteimprove.com/rules/sia-r90",
            "requirements": [
              {
                "uri": "https://www.w3.org/TR/WCAG/#info-and-relationships",
                "chapter": "1.3.1",
                "title": "Info and Relationships"
              },
              {
                "uri": "https://www.w3.org/TR/WCAG/#name-role-value",
                "chapter": "4.1.2",
                "title": "Name, Role, Value"
              }
            ]
          },
          "target": {
            "type": "element",
            "tagName": "li",
            "path": "/html[1]/body[1]/div[1]/main[1]/div[3]/div[1]/div[1]/ul[1]/li[5]",
            "codeLines": [
              "<li class=\"rec--tab\" role=\"tab\" aria-selected=\"false\" aria-controls=\"investments-panel\" id=\"investm...",
              "  <a href=\"javascript:void(0);\" class=\"tab-element\">",
              "    Investments",
              "  </a>",
              "</li>"
            ]
          }
        },
        {
          "index": 1099,
          "verdict": "failed",
          "rule": {
            "ruleID": "r90",
            "ruleSummary": "Element with presentational children has no focusable content",
            "scope": "component",
            "uri": "https://alfa.siteimprove.com/rules/sia-r90",
            "requirements": [
              {
                "uri": "https://www.w3.org/TR/WCAG/#info-and-relationships",
                "chapter": "1.3.1",
                "title": "Info and Relationships"
              },
              {
                "uri": "https://www.w3.org/TR/WCAG/#name-role-value",
                "chapter": "4.1.2",
                "title": "Name, Role, Value"
              }
            ]
          },
          "target": {
            "type": "element",
            "tagName": "li",
            "path": "/html[1]/body[1]/div[1]/main[1]/div[3]/div[1]/div[1]/ul[1]/li[6]",
            "codeLines": [
              "<li class=\"rec--tab\" role=\"tab\" aria-selected=\"false\" aria-controls=\"learning-panel\" id=\"learning\">",
              "  <a href=\"javascript:void(0);\" class=\"tab-element\">",
              "    Learning",
              "  </a>",
              "</li>"
            ]
          }
        }
      ]
    }
  ],
  "testTimes": [
    [
      "alfa",
      9
    ]
  ]
}